knxip
