Metadata-Version: 1.1
Name: knxip
Version: 0.5
Summary: A native Python KNX/IPNet implementation
Home-page: http://github.com/usul27/pknx
Author: Daniel Matuschek
Author-email: daniel@matuschek.net
License: MIT
Keywords: knx ip automation
Platform: UNKNOWN
Classifier: Development Status :: 3 - Alpha
Classifier: Intended Audience :: Developers
Classifier: Topic :: System :: Hardware :: Hardware Drivers
Classifier: License :: OSI Approved :: MIT License
Classifier: Programming Language :: Python :: 3
Classifier: Programming Language :: Python :: 3.4
Classifier: Programming Language :: Python :: 3.5
